klondbar/__init__.py
klondbar/megabar.py
klondbar/microbar.py
klondbar-0.1.4.dist-info/LICENSE
klondbar-0.1.4.dist-info/METADATA
klondbar-0.1.4.dist-info/WHEEL
klondbar-0.1.4.dist-info/top_level.txt
klondbar-0.1.4.dist-info/RECORD
