Metadata-Version: 2.1
Name: klondbar
Version: 0.1.4
Summary: A simple progress bar with lots of customization \(^-^)/
Home-page: https://gitlab.com/dariush-bahrami/klondbar_project.git
Author: dAriush Bahrami
Author-email: dariush.bahrami@ut.ac.ir
License: UNKNOWN
Platform: UNKNOWN
Classifier: Programming Language :: Python :: 3
Classifier: License :: OSI Approved :: GNU Affero General Public License v3
Classifier: Operating System :: OS Independent
Requires-Python: >=3.6
